<Texts Type="Other">
  <List>
    <Text Name="SonOfDestiny">
      <DisplayName>命运之子</DisplayName>
      <Desc>此人钟天地气运而生，是不折不扣的命运之子。</Desc>
    </Text>
    <Text Name="YinBody">
      <DisplayName>纯阴之体</DisplayName>
      <Desc>此人体质纯阴，寿命很短。但是却极有魅力，且拥有极佳的修行天赋。</Desc>
    </Text>
    <Text Name="YangBody">
      <DisplayName>纯阳之体</DisplayName>
      <Desc>此人体质纯阳，寿命悠长，天生好斗且极富魅力。但是他却很难控制自己的心境。</Desc>
    </Text>
    <Text Name="Cleanliness">
      <DisplayName>洁癖</DisplayName>
      <Desc>此人有洁癖。</Desc>
    </Text>
    <Text Name="Slovenly">
      <DisplayName>邋遢</DisplayName>
      <Desc>此人十分邋遢。</Desc>
    </Text>
    <Text Name="DragonBlood">
      <DisplayName>龙血者</DisplayName>
      <Desc>此人身体中有稀薄的龙之血脉，这让[IT]比他人敏锐且强壮。但这传承自先祖的野性也让[IT]更难控制自己的情绪。</Desc>
    </Text>
    <Text Name="DemonBlood">
      <DisplayName>魔血者</DisplayName>
      <Desc>此人身体中有稀薄的魔族血脉，这让[IT]对内气敏感。但也让[IT]的心境易受波动。</Desc>
    </Text>
    <Text Name="Realization">
      <DisplayName>觉悟</DisplayName>
      <Desc>虽然此人无法察觉自己是轮回者的事实，但[IT]依然拥有一种与生俱来的觉悟，这让他更好的专注眼下的生活。</Desc>
    </Text>
    <Text Name="Retarded">
      <DisplayName>智障</DisplayName>
      <Desc>智障特性标签</Desc>
    </Text>
    <Text Name="LunHui_1">
      <DisplayName>明察秋毫</DisplayName>
      <Desc>此人眼明如电，明察秋毫。</Desc>
    </Text>
    <Text Name="LunHui_2">
      <DisplayName>灵性</DisplayName>
      <Desc>此人深具灵性，拥有过人的悟性。</Desc>
    </Text>
    <Text Name="LunHui_3">
      <DisplayName>胸有大志</DisplayName>
      <Desc>此人一心向道，相比其他人更能耐得住修行之苦。</Desc>
    </Text>
    <Text Name="LunHui_4">
      <DisplayName>不眠者</DisplayName>
      <Desc>此人天赋异禀，精力充沛，熬夜不在话下。</Desc>
    </Text>
    <Text Name="LunHui_5">
      <DisplayName>龟速</DisplayName>
      <Desc>此人走的很慢，真的很慢。</Desc>
    </Text>
    <Text Name="LunHui_6">
      <DisplayName>穿越之人</DisplayName>
      <Desc>穿越的过程让此人拥有了漫长的寿命和不惧寒暑的特殊体质。</Desc>
    </Text>
    <Text Name="LunHui_7">
      <DisplayName>凤凰血脉</DisplayName>
      <Desc>此人秉承凤凰血脉出生，只是在修炼之法早已断绝的现代社会没什么用。</Desc>
    </Text>
    <Text Name="LunHui_8">
      <DisplayName>现代人</DisplayName>
      <Desc>来自现代的知识和思维虽然让[IT]在这个世界无比耀眼，也让[IT]无法胜任古代的很多工作。同时来自现代的眼光也让[IT]不可能爱上这个世界的任何人。</Desc>
    </Text>
    <Text Name="LunHui_9">
      <DisplayName>天生功德</DisplayName>
      <Desc>此人出生就带有大功德，上苍对其格外宽容。</Desc>
    </Text>
    <Text Name="LunHui_10">
      <DisplayName>现代人</DisplayName>
      <Desc>来自现代的知识和思维让[IT]拥有超人的知识，但对封建迷信的强烈抵触使[IT]修行之路倍加艰难。</Desc>
    </Text>
    <Text Name="LunHui_11">
      <DisplayName>现代人</DisplayName>
      <Desc>现代的生活让他习惯隐藏自己的存在，存在感极低的[IT]甚至被此界天道忽略，天生道行较少。习惯现代生活的[IT]无法胜任很多古代的工作，[IT]一心想通过飞升回归自己的世界，不愿在此界留情。</Desc>
    </Text>
    <Text Name="LunHui_12">
      <DisplayName>人定胜天</DisplayName>
      <Desc>此人以四十年如一日的苦练弥补了天缺之体，为修行打下了坚实的基础。这些经历也让他比别人更能耐得住修行之苦。</Desc>
    </Text>
    <Text Name="LunHui_13">
      <DisplayName>摸鱼</DisplayName>
      <Desc>[IT]做事不紧不慢，经常路上瞎晃悠。</Desc>
    </Text>
    <Text Name="LunHui_14">
      <DisplayName>策划</DisplayName>
      <Desc>常年的办公室生活让他不擅长劳作。然而丰富的想象力让他快速的融入了这个世界。</Desc>
    </Text>
    <Text Name="LunHui_15">
      <DisplayName>邪息入体</DisplayName>
      <Desc>此人层因修炼邪门功法而获得奇特的体质，虽然筑基比他人更难，但是他的潜力却超过旁人。</Desc>
    </Text>
    <Text Name="LunHui_16">
      <DisplayName>神授</DisplayName>
      <Desc>此人曾被仙人托梦，改换了体质，拥有悠长的寿命。</Desc>
    </Text>
    <Text Name="LunHui_17">
      <DisplayName>剑痴</DisplayName>
      <Desc>此人骨子里嗜剑如命，简直可以称得上是为剑而生。</Desc>
    </Text>
    <Text Name="LunHui_18">
      <DisplayName>现代人</DisplayName>
      <Desc>常年的现代生活让他体质孱弱，但他却拥有开阔的视野和先进的思维方式。</Desc>
    </Text>
    <Text Name="LunHui_19">
      <DisplayName>踏雪无痕</DisplayName>
      <Desc>此人从飞貂身上领悟出踏雪无痕的步伐，这让他移动速度远超常人。</Desc>
    </Text>
    <Text Name="LunHui_20">
      <DisplayName>仗义</DisplayName>
      <Desc>此人为人仗义，让别人心生好感。</Desc>
    </Text>
    <Text Name="LunHui_21">
      <DisplayName>鲁莽</DisplayName>
      <Desc>此人鲁莽，做事大大咧咧，易冲动。</Desc>
    </Text>
    <Text Name="LunHui_22">
      <DisplayName>胆小</DisplayName>
      <Desc>此人胆小，做事十分谨慎。</Desc>
    </Text>
    <Text Name="LunHui_23">
      <DisplayName>掠草惊风</DisplayName>
      <Desc>此人身法迅速，移动速度十分迅捷。</Desc>
    </Text>
    <Text Name="LunHui_24">
      <DisplayName>嗜睡</DisplayName>
      <Desc>此人很喜欢睡觉，动不动就犯困。</Desc>
    </Text>
    <Text Name="LunHui_25">
      <DisplayName>魏晋之风</DisplayName>
      <Desc>此人有魏晋风骨，学识渊博，有独特的魅力。</Desc>
    </Text>
    <Text Name="LunHui_26">
      <DisplayName>骨头爱好者</DisplayName>
      <Desc>此人对骨头有狂热的兴趣。</Desc>
    </Text>
    <Text Name="LunHui_27">
      <DisplayName>渔民</DisplayName>
      <Desc>此人擅长捕鱼，眼疾手快。</Desc>
    </Text>
    <Text Name="LunHui_28">
      <DisplayName>塞壬之歌</DisplayName>
      <Desc>此人歌声美妙，如传说中的塞壬一般具有魔力。</Desc>
    </Text>
    <Text Name="LunHui_29">
      <DisplayName>文艺青年</DisplayName>
      <Desc>此人拥有丰富的情感和敏感的内心，[IT]天生拥有超人的想象力。</Desc>
    </Text>
    <Text Name="LunHui_30">
      <DisplayName>悠闲</DisplayName>
      <Desc>此人胸有成竹，时刻都看上去很悠闲，从不显慌乱。</Desc>
    </Text>
    <Text Name="LunHui_31">
      <DisplayName>背锅侠</DisplayName>
      <Desc>此人被动接锅，深的大家喜爱。</Desc>
    </Text>
    <Text Name="LunHui_32">
      <DisplayName>幸运儿</DisplayName>
      <Desc>此人天生的幸运儿，让人羡慕。</Desc>
    </Text>
    <Text Name="LunHui_33">
      <DisplayName>抖S</DisplayName>
      <Desc>此人是个抖S，emmm。</Desc>
    </Text>
    <Text Name="LunHui_34">
      <DisplayName>气运超群</DisplayName>
      <Desc>此人天生的气运超群。</Desc>
    </Text>
    <Text Name="LunHui_35">
      <DisplayName>动物之友</DisplayName>
      <Desc>此人热爱动物，不能从事狩猎工作。</Desc>
    </Text>
    <Text Name="LunHui_36">
      <DisplayName>未来科技</DisplayName>
      <Desc>此人掌握着未来科技的奥义，工作效率更高，移动速度更快。</Desc>
    </Text>
    <Text Name="LunHui_37">
      <DisplayName>董事长</DisplayName>
      <Desc>作为深得民心的董事长，深得员工们的喜爱。</Desc>
    </Text>
    <Text Name="LunHui_38">
      <DisplayName>灵巧侠盗</DisplayName>
      <Desc>此人是个侠盗，心怀正义，身法迅捷。</Desc>
    </Text>
    <Text Name="LunHui_39">
      <DisplayName>散人干不死</DisplayName>
      <Desc>此人有过人的韧性，耐寒耐热，身手敏捷，寿元悠长。</Desc>
    </Text>
    <Text Name="LunHui_40">
      <DisplayName>强迫症</DisplayName>
      <Desc>此人有强迫症，做事儿很慢，但是做的比较好。</Desc>
    </Text>
    <Text Name="LunHui_41">
      <DisplayName>侠义豪爽</DisplayName>
      <Desc>此人侠义心肠，性格豪爽，让人一见便心生好感。</Desc>
    </Text>
    <Text Name="LunHui_42">
      <DisplayName>神厨</DisplayName>
      <Desc>此人厨艺盖世。</Desc>
    </Text>
    <Text Name="LunHui_43">
      <DisplayName>完美主义</DisplayName>
      <Desc>此人有完美主义，做事儿很慢，但是做的比较好。</Desc>
    </Text>
    <Text Name="LunHui_44">
      <DisplayName>三百六十行</DisplayName>
      <Desc>对什么都感兴趣，做啥都开心。</Desc>
    </Text>
    <Text Name="LunHui_45">
      <DisplayName>神行百变</DisplayName>
      <Desc>此人行动敏捷，目光如电。</Desc>
    </Text>
    <Text Name="LunHui_46">
      <DisplayName>腹语术</DisplayName>
      <Desc>此人不爱开口，以腹语术与人交流。</Desc>
    </Text>
    <Text Name="LunHui_47">
      <DisplayName>人在江湖</DisplayName>
      <Desc>此人天生的江湖人。</Desc>
    </Text>
    <Text Name="LunHui_48">
      <DisplayName>受欢迎</DisplayName>
      <Desc>此人天生受到所有人欢迎！</Desc>
    </Text>
    <Text Name="LunHui_49">
      <DisplayName>失忆</DisplayName>
      <Desc>此人忘记了过去，只享受现在的生活！</Desc>
    </Text>
    <Text Name="LunHui_50">
      <DisplayName>咕咕咕</DisplayName>
      <Desc>咕咕咕</Desc>
    </Text>
    <Text Name="LunHui_51">
      <DisplayName>天赋异禀</DisplayName>
      <Desc>此人天赋异禀，天生耐寒耐热，颇具修行资质。</Desc>
    </Text>
    <Text Name="LunHui_52">
      <DisplayName>痔之诅咒</DisplayName>
      <Desc>此人被命运诅咒，永远被痔疮困扰。</Desc>
    </Text>
    <Text Name="LunHui_53">
      <DisplayName>懒人</DisplayName>
      <Desc>不可能做苦力的，一辈子也不可能做苦力的！</Desc>
    </Text>
    <Text Name="LunHui_54">
      <DisplayName>长度惊人</DisplayName>
      <Desc>此人长度惊人，让人叹为观止。</Desc>
    </Text>
    <Text Name="LunHui_55">
      <DisplayName>夜观星象</DisplayName>
      <Desc>此人常年夜观星象，练成了几乎不怎么睡觉的强大本领。</Desc>
    </Text>
    <Text Name="LunHui_56">
      <DisplayName>嘴炮</DisplayName>
      <Desc>此人嘴炮功力十足，非常擅长说服别人。</Desc>
    </Text>
    <Text Name="LunHui_57">
      <DisplayName>修行之种</DisplayName>
      <Desc>此人天赋异禀，颇具修行资质。</Desc>
    </Text>
    <Text Name="LunHui_58">
      <DisplayName>真实</DisplayName>
      <Desc>此人的真实经历令其他人刮目相看。</Desc>
    </Text>
    <Text Name="LunHui_59">
      <DisplayName>科学</DisplayName>
      <Desc>此人的科学经历令他心中充满信念。</Desc>
    </Text>
    <Text Name="LunHui_60">
      <DisplayName>天赋异禀</DisplayName>
      <Desc>此人天赋异禀，聪慧过人，学东西很快。</Desc>
    </Text>
    <Text Name="LunHui_61">
      <DisplayName>医者仁心</DisplayName>
      <Desc>此人医术高明，以救死扶伤为己任。</Desc>
    </Text>
    <Text Name="LunHui_62">
      <DisplayName>修仙狂魔</DisplayName>
      <Desc>此人一心修仙，每天修仙15小时以上，如疯似魔。</Desc>
    </Text>
    <Text Name="LunHui_63">
      <DisplayName>神匠</DisplayName>
      <Desc>此人天赋异禀，制作物品品质很高。</Desc>
    </Text>
    <Text Name="LunHui_64">
      <DisplayName>丹青</DisplayName>
    </Text>
    <Text Name="LunHui_65">
      <DisplayName>画符师</DisplayName>
      <Desc>此人亲手画过无数符咒，可称画符宗师。</Desc>
    </Text>
    <Text Name="LunHui_Kong_1">
      <DisplayName>傲娇</DisplayName>
      <Desc>此人性格十分别扭，对别人关心却无法说出口。</Desc>
    </Text>
    <Text Name="LunHui_Kong_2">
      <DisplayName>毒舌</DisplayName>
      <Desc>此人嘴巴十分毒，经常噎的别人说不出话。</Desc>
    </Text>
    <Text Name="LunHui_Kong_3">
      <DisplayName>正直</DisplayName>
      <Desc>此人十分正直。</Desc>
    </Text>
    <Text Name="LunHui_Kong_4">
      <DisplayName>狡猾</DisplayName>
      <Desc>此人十分狡猾，对谁都不信任。</Desc>
    </Text>
    <Text Name="LunHui_Kong_5">
      <DisplayName>爱唱歌</DisplayName>
      <Desc>此人自信而奔放，很爱唱歌。</Desc>
    </Text>
    <Text Name="LunHui_Kong_6">
      <DisplayName>执着</DisplayName>
      <Desc>此人拥有坚韧的意志，更能对抗修行的迷惘。</Desc>
    </Text>
    <Text Name="LunHui_Kong_7">
      <DisplayName>声线迷人</DisplayName>
      <Desc>此人拥有迷人的声线，让人听了之后情不自禁的身心放松。</Desc>
    </Text>
    <Text Name="LunHui_Kong_8">
      <DisplayName>不善交际</DisplayName>
      <Desc>此人长期自闭，不善交际。</Desc>
    </Text>
    <Text Name="LunHui_Kong_9">
      <DisplayName>寿命补正</DisplayName>
    </Text>
    <Text Name="LunHui_Kong_10">
      <DisplayName>演技出众</DisplayName>
      <Desc>此人天赋异禀，演技出众！</Desc>
    </Text>
    <Text Name="LunHui_Kong_11">
      <DisplayName>八卦</DisplayName>
      <Desc>这个人很八卦，对什么事儿都喜欢打听。</Desc>
    </Text>
    <Text Name="LunHui_Kong_12">
      <DisplayName>寿命补正大</DisplayName>
    </Text>
    <Text Name="LunHui_Kong_13">
      <DisplayName>偷天换日</DisplayName>
      <Desc>此人拥有万里无一偷天换日之命格，他似乎被老天遗忘，天生寿元极长。</Desc>
    </Text>
    <Text Name="LunHui_Kong_14">
      <DisplayName>掌门</DisplayName>
      <Desc>直播间道友爱称。</Desc>
    </Text>
    <Text Name="Sys_YuSheTeXing1">
      <DisplayName>预设1</DisplayName>
    </Text>
    <Text Name="Sys_YuSheTeXing2">
      <DisplayName>预设2</DisplayName>
    </Text>
    <Text Name="Sys_YuSheTeXing3">
      <DisplayName>预设3</DisplayName>
    </Text>
    <Text Name="Sys_YuSheTeXing4">
      <DisplayName>预设4</DisplayName>
    </Text>
  </List>
</Texts>